ticktick_mcp/__init__.py
ticktick_mcp/authenticate.py
ticktick_mcp/cli.py
mseep_mseep_ticktick_mcp-0.1.0.dist-info/METADATA
mseep_mseep_ticktick_mcp-0.1.0.dist-info/WHEEL
mseep_mseep_ticktick_mcp-0.1.0.dist-info/top_level.txt
mseep_mseep_ticktick_mcp-0.1.0.dist-info/RECORD
